[{"pickup_community_area":"1","hour_of_day":"6","min_of_day":"15","cost_per_min":"0.8905871872"}
,{"pickup_community_area":"2","hour_of_day":"6","min_of_day":"15","cost_per_min":"0.8539749488"}
,{"pickup_community_area":"3","hour_of_day":"6","min_of_day":"15","cost_per_min":"1.043863232"}
,{"pickup_community_area":"4","hour_of_day":"6","min_of_day":"15","cost_per_min":"0.9226417854"}
,{"pickup_community_area":"5","hour_of_day":"6","min_of_day":"15","cost_per_min":"1.07264473"}
,{"pickup_community_area":"6","hour_of_day":"6","min_of_day":"15","cost_per_min":"1.151487006"}
,{"pickup_community_area":"7","hour_of_day":"6","min_of_day":"15","cost_per_min":"1.198368405"}
,{"pickup_community_area":"8","hour_of_day":"6","min_of_day":"15","cost_per_min":"1.372667333"}
,{"pickup_community_area":"9","hour_of_day":"6","min_of_day":"15","cost_per_min":"0.9099530524"}
,{"pickup_community_area":"10","hour_of_day":"6","min_of_day":"15","cost_per_min":"0.898911932"}
,{"pickup_community_area":"11","hour_of_day":"6","min_of_day":"15","cost_per_min":"0.9534723746"}
,{"pickup_community_area":"12","hour_of_day":"6","min_of_day":"15","cost_per_min":"0.9619399375"}
,{"pickup_community_area":"13","hour_of_day":"6","min_of_day":"15","cost_per_min":"0.8779865481"}
,{"pickup_community_area":"14","hour_of_day":"6","min_of_day":"15","cost_per_min":"0.8580198218"}
,{"pickup_community_area":"15","hour_of_day":"6","min_of_day":"15","cost_per_min":"0.8286460227"}
,{"pickup_community_area":"16","hour_of_day":"6","min_of_day":"15","cost_per_min":"0.9375945573"}
,{"pickup_community_area":"17","hour_of_day":"6","min_of_day":"15","cost_per_min":"0.7593741199"}
,{"pickup_community_area":"18","hour_of_day":"6","min_of_day":"15","cost_per_min":"0.7886798777"}
,{"pickup_community_area":"19","hour_of_day":"6","min_of_day":"15","cost_per_min":"0.7588407226"}
,{"pickup_community_area":"20","hour_of_day":"6","min_of_day":"15","cost_per_min":"0.8088993562"}
,{"pickup_community_area":"21","hour_of_day":"6","min_of_day":"15","cost_per_min":"0.9867963521"}
,{"pickup_community_area":"22","hour_of_day":"6","min_of_day":"15","cost_per_min":"1.053875549"}
,{"pickup_community_area":"23","hour_of_day":"6","min_of_day":"15","cost_per_min":"0.8974966139"}
,{"pickup_community_area":"24","hour_of_day":"6","min_of_day":"15","cost_per_min":"1.151720115"}
,{"pickup_community_area":"25","hour_of_day":"6","min_of_day":"15","cost_per_min":"0.8635192317"}
,{"pickup_community_area":"26","hour_of_day":"6","min_of_day":"15","cost_per_min":"1.009406583"}
,{"pickup_community_area":"27","hour_of_day":"6","min_of_day":"15","cost_per_min":"1.004047675"}
,{"pickup_community_area":"28","hour_of_day":"6","min_of_day":"15","cost_per_min":"1.210086211"}
,{"pickup_community_area":"29","hour_of_day":"6","min_of_day":"15","cost_per_min":"0.9400610239"}
,{"pickup_community_area":"30","hour_of_day":"6","min_of_day":"15","cost_per_min":"0.8853802632"}
,{"pickup_community_area":"31","hour_of_day":"6","min_of_day":"15","cost_per_min":"0.9628771465"}
,{"pickup_community_area":"32","hour_of_day":"6","min_of_day":"15","cost_per_min":"1.357665251"}
,{"pickup_community_area":"33","hour_of_day":"6","min_of_day":"15","cost_per_min":"1.192796629"}
,{"pickup_community_area":"34","hour_of_day":"6","min_of_day":"15","cost_per_min":"1.167907071"}
,{"pickup_community_area":"35","hour_of_day":"6","min_of_day":"15","cost_per_min":"1.013040741"}
,{"pickup_community_area":"36","hour_of_day":"6","min_of_day":"15","cost_per_min":"1.040589519"}
,{"pickup_community_area":"37","hour_of_day":"6","min_of_day":"15","cost_per_min":"1.024646186"}
,{"pickup_community_area":"38","hour_of_day":"6","min_of_day":"15","cost_per_min":"0.9913985864"}
,{"pickup_community_area":"39","hour_of_day":"6","min_of_day":"15","cost_per_min":"1.106452628"}
,{"pickup_community_area":"40","hour_of_day":"6","min_of_day":"15","cost_per_min":"0.9734138928"}
,{"pickup_community_area":"41","hour_of_day":"6","min_of_day":"15","cost_per_min":"1.104292491"}
,{"pickup_community_area":"42","hour_of_day":"6","min_of_day":"15","cost_per_min":"1.011695434"}
,{"pickup_community_area":"43","hour_of_day":"6","min_of_day":"15","cost_per_min":"0.9756467172"}
,{"pickup_community_area":"44","hour_of_day":"6","min_of_day":"15","cost_per_min":"0.9588824711"}
,{"pickup_community_area":"45","hour_of_day":"6","min_of_day":"15","cost_per_min":"0.9616221268"}
,{"pickup_community_area":"46","hour_of_day":"6","min_of_day":"15","cost_per_min":"0.9358048059"}
,{"pickup_community_area":"47","hour_of_day":"6","min_of_day":"15","cost_per_min":"0.862681265"}
,{"pickup_community_area":"48","hour_of_day":"6","min_of_day":"15","cost_per_min":"0.9124228063"}
,{"pickup_community_area":"49","hour_of_day":"6","min_of_day":"15","cost_per_min":"0.9315486934"}
,{"pickup_community_area":"50","hour_of_day":"6","min_of_day":"15","cost_per_min":"0.8592398745"}
,{"pickup_community_area":"51","hour_of_day":"6","min_of_day":"15","cost_per_min":"0.9254300854"}
,{"pickup_community_area":"52","hour_of_day":"6","min_of_day":"15","cost_per_min":"0.9100242163"}
,{"pickup_community_area":"53","hour_of_day":"6","min_of_day":"15","cost_per_min":"0.8622513541"}
,{"pickup_community_area":"54","hour_of_day":"6","min_of_day":"15","cost_per_min":"0.853594643"}
,{"pickup_community_area":"55","hour_of_day":"6","min_of_day":"15","cost_per_min":"0.8317029821"}
,{"pickup_community_area":"56","hour_of_day":"6","min_of_day":"15","cost_per_min":"0.8522097592"}
,{"pickup_community_area":"57","hour_of_day":"6","min_of_day":"15","cost_per_min":"0.8157513431"}
,{"pickup_community_area":"58","hour_of_day":"6","min_of_day":"15","cost_per_min":"0.8639824293"}
,{"pickup_community_area":"59","hour_of_day":"6","min_of_day":"15","cost_per_min":"0.8835401743"}
,{"pickup_community_area":"60","hour_of_day":"6","min_of_day":"15","cost_per_min":"0.9625257385"}
,{"pickup_community_area":"61","hour_of_day":"6","min_of_day":"15","cost_per_min":"0.8766194183"}
,{"pickup_community_area":"62","hour_of_day":"6","min_of_day":"15","cost_per_min":"0.7687745944"}
,{"pickup_community_area":"63","hour_of_day":"6","min_of_day":"15","cost_per_min":"0.7907646638"}
,{"pickup_community_area":"64","hour_of_day":"6","min_of_day":"15","cost_per_min":"0.784486658"}
,{"pickup_community_area":"65","hour_of_day":"6","min_of_day":"15","cost_per_min":"0.8087922231"}
,{"pickup_community_area":"66","hour_of_day":"6","min_of_day":"15","cost_per_min":"0.7987040853"}
,{"pickup_community_area":"67","hour_of_day":"6","min_of_day":"15","cost_per_min":"0.857229334"}
,{"pickup_community_area":"68","hour_of_day":"6","min_of_day":"15","cost_per_min":"0.9261512735"}
,{"pickup_community_area":"69","hour_of_day":"6","min_of_day":"15","cost_per_min":"0.9554658002"}
,{"pickup_community_area":"70","hour_of_day":"6","min_of_day":"15","cost_per_min":"0.7759505058"}
,{"pickup_community_area":"71","hour_of_day":"6","min_of_day":"15","cost_per_min":"0.8881687127"}
,{"pickup_community_area":"72","hour_of_day":"6","min_of_day":"15","cost_per_min":"0.9127429563"}
,{"pickup_community_area":"73","hour_of_day":"6","min_of_day":"15","cost_per_min":"0.9054265872"}
,{"pickup_community_area":"74","hour_of_day":"6","min_of_day":"15","cost_per_min":"0.9039009404"}
,{"pickup_community_area":"75","hour_of_day":"6","min_of_day":"15","cost_per_min":"0.9003800842"}
,{"pickup_community_area":"76","hour_of_day":"6","min_of_day":"15","cost_per_min":"0.9150341593"}
,{"pickup_community_area":"77","hour_of_day":"6","min_of_day":"15","cost_per_min":"0.9906530893"}]