[{"pickup_community_area":"1","hour_of_day":"22","min_of_day":"45","cost_per_min":"0.8839385214"}
,{"pickup_community_area":"2","hour_of_day":"22","min_of_day":"45","cost_per_min":"0.8614898502"}
,{"pickup_community_area":"3","hour_of_day":"22","min_of_day":"45","cost_per_min":"1.146437099"}
,{"pickup_community_area":"4","hour_of_day":"22","min_of_day":"45","cost_per_min":"0.9373510124"}
,{"pickup_community_area":"5","hour_of_day":"22","min_of_day":"45","cost_per_min":"1.048392781"}
,{"pickup_community_area":"6","hour_of_day":"22","min_of_day":"45","cost_per_min":"1.263861624"}
,{"pickup_community_area":"7","hour_of_day":"22","min_of_day":"45","cost_per_min":"1.280698075"}
,{"pickup_community_area":"8","hour_of_day":"22","min_of_day":"45","cost_per_min":"1.607967694"}
,{"pickup_community_area":"9","hour_of_day":"22","min_of_day":"45","cost_per_min":"1.028377398"}
,{"pickup_community_area":"10","hour_of_day":"22","min_of_day":"45","cost_per_min":"0.9753530723"}
,{"pickup_community_area":"11","hour_of_day":"22","min_of_day":"45","cost_per_min":"0.9361048253"}
,{"pickup_community_area":"12","hour_of_day":"22","min_of_day":"45","cost_per_min":"0.9528830221"}
,{"pickup_community_area":"13","hour_of_day":"22","min_of_day":"45","cost_per_min":"0.8412683079"}
,{"pickup_community_area":"14","hour_of_day":"22","min_of_day":"45","cost_per_min":"0.8780757804"}
,{"pickup_community_area":"15","hour_of_day":"22","min_of_day":"45","cost_per_min":"0.9365140477"}
,{"pickup_community_area":"16","hour_of_day":"22","min_of_day":"45","cost_per_min":"0.9710163501"}
,{"pickup_community_area":"17","hour_of_day":"22","min_of_day":"45","cost_per_min":"0.83748542"}
,{"pickup_community_area":"18","hour_of_day":"22","min_of_day":"45","cost_per_min":"0.8388092897"}
,{"pickup_community_area":"19","hour_of_day":"22","min_of_day":"45","cost_per_min":"0.8738011894"}
,{"pickup_community_area":"20","hour_of_day":"22","min_of_day":"45","cost_per_min":"0.886264549"}
,{"pickup_community_area":"21","hour_of_day":"22","min_of_day":"45","cost_per_min":"1.043602877"}
,{"pickup_community_area":"22","hour_of_day":"22","min_of_day":"45","cost_per_min":"1.169445006"}
,{"pickup_community_area":"23","hour_of_day":"22","min_of_day":"45","cost_per_min":"0.9617246652"}
,{"pickup_community_area":"24","hour_of_day":"22","min_of_day":"45","cost_per_min":"1.389080342"}
,{"pickup_community_area":"25","hour_of_day":"22","min_of_day":"45","cost_per_min":"0.963206596"}
,{"pickup_community_area":"26","hour_of_day":"22","min_of_day":"45","cost_per_min":"1.123934774"}
,{"pickup_community_area":"27","hour_of_day":"22","min_of_day":"45","cost_per_min":"1.201761145"}
,{"pickup_community_area":"28","hour_of_day":"22","min_of_day":"45","cost_per_min":"1.776569574"}
,{"pickup_community_area":"29","hour_of_day":"22","min_of_day":"45","cost_per_min":"1.517357873"}
,{"pickup_community_area":"30","hour_of_day":"22","min_of_day":"45","cost_per_min":"1.210568898"}
,{"pickup_community_area":"31","hour_of_day":"22","min_of_day":"45","cost_per_min":"1.383563557"}
,{"pickup_community_area":"32","hour_of_day":"22","min_of_day":"45","cost_per_min":"1.773028305"}
,{"pickup_community_area":"33","hour_of_day":"22","min_of_day":"45","cost_per_min":"1.502087562"}
,{"pickup_community_area":"34","hour_of_day":"22","min_of_day":"45","cost_per_min":"1.470109958"}
,{"pickup_community_area":"35","hour_of_day":"22","min_of_day":"45","cost_per_min":"1.243073672"}
,{"pickup_community_area":"36","hour_of_day":"22","min_of_day":"45","cost_per_min":"1.147339746"}
,{"pickup_community_area":"37","hour_of_day":"22","min_of_day":"45","cost_per_min":"1.302867055"}
,{"pickup_community_area":"38","hour_of_day":"22","min_of_day":"45","cost_per_min":"1.146666179"}
,{"pickup_community_area":"39","hour_of_day":"22","min_of_day":"45","cost_per_min":"1.177344937"}
,{"pickup_community_area":"40","hour_of_day":"22","min_of_day":"45","cost_per_min":"1.177396897"}
,{"pickup_community_area":"41","hour_of_day":"22","min_of_day":"45","cost_per_min":"1.648954945"}
,{"pickup_community_area":"42","hour_of_day":"22","min_of_day":"45","cost_per_min":"1.317526026"}
,{"pickup_community_area":"43","hour_of_day":"22","min_of_day":"45","cost_per_min":"0.9962788538"}
,{"pickup_community_area":"44","hour_of_day":"22","min_of_day":"45","cost_per_min":"1.109412257"}
,{"pickup_community_area":"45","hour_of_day":"22","min_of_day":"45","cost_per_min":"1.046099307"}
,{"pickup_community_area":"46","hour_of_day":"22","min_of_day":"45","cost_per_min":"0.9308812224"}
,{"pickup_community_area":"47","hour_of_day":"22","min_of_day":"45","cost_per_min":"0.9657845833"}
,{"pickup_community_area":"48","hour_of_day":"22","min_of_day":"45","cost_per_min":"1.030486809"}
,{"pickup_community_area":"49","hour_of_day":"22","min_of_day":"45","cost_per_min":"1.075948613"}
,{"pickup_community_area":"50","hour_of_day":"22","min_of_day":"45","cost_per_min":"1.035873978"}
,{"pickup_community_area":"51","hour_of_day":"22","min_of_day":"45","cost_per_min":"1.009377079"}
,{"pickup_community_area":"52","hour_of_day":"22","min_of_day":"45","cost_per_min":"1.134624206"}
,{"pickup_community_area":"53","hour_of_day":"22","min_of_day":"45","cost_per_min":"0.9723576903"}
,{"pickup_community_area":"54","hour_of_day":"22","min_of_day":"45","cost_per_min":"0.9486969305"}
,{"pickup_community_area":"55","hour_of_day":"22","min_of_day":"45","cost_per_min":"0.8725779824"}
,{"pickup_community_area":"56","hour_of_day":"22","min_of_day":"45","cost_per_min":"1.512212412"}
,{"pickup_community_area":"57","hour_of_day":"22","min_of_day":"45","cost_per_min":"1.019937588"}
,{"pickup_community_area":"58","hour_of_day":"22","min_of_day":"45","cost_per_min":"1.062129033"}
,{"pickup_community_area":"59","hour_of_day":"22","min_of_day":"45","cost_per_min":"1.09469932"}
,{"pickup_community_area":"60","hour_of_day":"22","min_of_day":"45","cost_per_min":"1.231213235"}
,{"pickup_community_area":"61","hour_of_day":"22","min_of_day":"45","cost_per_min":"1.07488416"}
,{"pickup_community_area":"62","hour_of_day":"22","min_of_day":"45","cost_per_min":"0.9680752774"}
,{"pickup_community_area":"63","hour_of_day":"22","min_of_day":"45","cost_per_min":"1.012239345"}
,{"pickup_community_area":"64","hour_of_day":"22","min_of_day":"45","cost_per_min":"1.046323249"}
,{"pickup_community_area":"65","hour_of_day":"22","min_of_day":"45","cost_per_min":"1.005257029"}
,{"pickup_community_area":"66","hour_of_day":"22","min_of_day":"45","cost_per_min":"0.9771175884"}
,{"pickup_community_area":"67","hour_of_day":"22","min_of_day":"45","cost_per_min":"1.037833251"}
,{"pickup_community_area":"68","hour_of_day":"22","min_of_day":"45","cost_per_min":"1.125049498"}
,{"pickup_community_area":"69","hour_of_day":"22","min_of_day":"45","cost_per_min":"1.147270963"}
,{"pickup_community_area":"70","hour_of_day":"22","min_of_day":"45","cost_per_min":"0.9162843269"}
,{"pickup_community_area":"71","hour_of_day":"22","min_of_day":"45","cost_per_min":"1.058036876"}
,{"pickup_community_area":"72","hour_of_day":"22","min_of_day":"45","cost_per_min":"1.143869163"}
,{"pickup_community_area":"73","hour_of_day":"22","min_of_day":"45","cost_per_min":"1.056733606"}
,{"pickup_community_area":"74","hour_of_day":"22","min_of_day":"45","cost_per_min":"1.146284279"}
,{"pickup_community_area":"75","hour_of_day":"22","min_of_day":"45","cost_per_min":"1.013129723"}
,{"pickup_community_area":"76","hour_of_day":"22","min_of_day":"45","cost_per_min":"1.495353062"}
,{"pickup_community_area":"77","hour_of_day":"22","min_of_day":"45","cost_per_min":"0.9736136227"}]